{
"type": "FeatureCollection",
"name": "cotonou_points",
"crs": { "type": "name", "properties": { "name": "urn:ogc:def:crs:OGC:1.3:CRS84" } },
"features": [
{ "type": "Feature", "properties": { "Quartier": "Akpakpa", "Latitude": 6.367, "Longitude": 2.45 }, "geometry": { "type": "Point", "coordinates": [ 2.45, 6.367 ] } },
{ "type": "Feature", "properties": { "Quartier": "Cadjehoun", "Latitude": 6.358, "Longitude": 2.395 }, "geometry": { "type": "Point", "coordinates": [ 2.395, 6.358 ] } },
{ "type": "Feature", "properties": { "Quartier": "Fidjrosse", "Latitude": 6.363, "Longitude": 2.36 }, "geometry": { "type": "Point", "coordinates": [ 2.36, 6.363 ] } },
{ "type": "Feature", "properties": { "Quartier": "Etoile", "Latitude": 6.369, "Longitude": 2.431 }, "geometry": { "type": "Point", "coordinates": [ 2.431, 6.369 ] } },
{ "type": "Feature", "properties": { "Quartier": "Zongo", "Latitude": 6.362, "Longitude": 2.42 }, "geometry": { "type": "Point", "coordinates": [ 2.42, 6.362 ] } },
{ "type": "Feature", "properties": { "Quartier": "Calavi", "Latitude": 6.448, "Longitude": 2.348 }, "geometry": { "type": "Point", "coordinates": [ 2.348, 6.448 ] } }
]
}
